bots/__about__.py
bots/__init__.py
bots/admin.py
bots/apachewebserver.py
bots/automaticmaintenance.py
bots/bots_context.py
bots/botsconfig.py
bots/botsglobal.py
bots/botsinit.py
bots/botslib.py
bots/botssqlite.py
bots/botsupdatedb.py
bots/cleanup.py
bots/communication.py
bots/dirmonitor.py
bots/engine.py
bots/engine2.py
bots/envelope.py
bots/forms.py
bots/grammar.py
bots/grammarcheck.py
bots/inmessage.py
bots/job2queue.py
bots/jobqueueserver.py
bots/message.py
bots/models.py
bots/node.py
bots/outmessage.py
bots/persistfilters.py
bots/pluglib.py
bots/plugoutindex.py
bots/preprocess.py
bots/py2html.py
bots/router.py
bots/transform.py
bots/urls.py
bots/validate_email.py
bots/viewlib.py
bots/views.py
bots/webserver.py
bots/xml2botsgrammar.py
bots/config/__init__.py
bots/config/bots.ini
bots/config/settings.py
bots/install/bots.ini
bots/install/botsdb
bots/install/settings.py
bots/locale/nl/LC_MESSAGES/django.mo
bots/locale/nl/LC_MESSAGES/django.po
bots/sql/mutex.mysql.sql
bots/sql/mutex.postgresql_psycopg2.sql
bots/sql/mutex.sqlite3.sql
bots/sql/persist.mysql.sql
bots/sql/persist.postgresql_psycopg2.sql
bots/sql/persist.sqlite3.sql
bots/sql/ta.mysql.sql
bots/sql/ta.postgresql_psycopg2.sql
bots/sql/ta.sqlite3.sql
bots/sql/uniek.sql
bots/static/css/bots.css
bots/static/css/jquery.datetimepicker.min.css
bots/static/images/botslogo.png
bots/static/images/favicon.ico
bots/static/images/icon-pass.gif
bots/static/images/icon-pass_parse.gif
bots/static/images/logfiler.png
bots/static/images/star.png
bots/static/js/jquery.datetimepicker.full.min.js
bots/templates/404.html
bots/templates/500.html
bots/templates/admin/base.html
bots/templates/admin/base_site.html
bots/templates/admin/submit_line.html
bots/templates/bots/about.html
bots/templates/bots/botslogo.html
bots/templates/bots/confirm.html
bots/templates/bots/delete.html
bots/templates/bots/detail.html
bots/templates/bots/document.html
bots/templates/bots/filer.html
bots/templates/bots/incoming.html
bots_ediint-3.3.1.dist-info/METADATA
bots_ediint-3.3.1.dist-info/WHEEL
bots_ediint-3.3.1.dist-info/entry_points.txt
bots_ediint-3.3.1.dist-info/license.rst
bots_ediint-3.3.1.dist-info/top_level.txt
bots_ediint-3.3.1.dist-info/RECORD
